webcomment/__init__.py
webcomment/admin.py
webcomment/apps.py
webcomment/resolver.py
webcomment/saas_permissions.py
webcomment/serializers.py
webcomment/settings.py
webcomment/signals.py
webcomment/tasks.py
webcomment/api_urls/__init__.py
webcomment/api_urls/all.py
webcomment/api_urls/comments.py
webcomment/api_urls/reactions.py
webcomment/api_urls/settings.py
webcomment/api_urls/threads.py
webcomment/endpoints/__init__.py
webcomment/endpoints/comments.py
webcomment/endpoints/reactions.py
webcomment/endpoints/settings.py
webcomment/endpoints/threads.py
webcomment/fixtures/test_data.yaml
webcomment/migrations/0001_initial.py
webcomment/migrations/__init__.py
webcomment/models/__init__.py
webcomment/models/comment.py
webcomment/models/reaction.py
webcomment/models/setting.py
webcomment/models/thread.py
webcomment/registry/__init__.py
webcomment/registry/default_roles.py
webcomment/registry/default_scopes.py
webcomment/webmention/__init__.py
webcomment/webmention/actions.py
webcomment/webmention/parser.py
webcomment/webmention/urls.py
webcomment/webmention/views.py
webcomment/widget/__init__.py
webcomment/widget/endpoints.py
webcomment/widget/serializers.py
webcomment/widget/turnstile.py
webcomment/widget/urls.py
webcomment-0.4.2.dist-info/METADATA
webcomment-0.4.2.dist-info/WHEEL
webcomment-0.4.2.dist-info/RECORD
